{
  "Routes": [
    {
      "DownstreamPathTemplate": "/connect/token",
      "DownstreamScheme": "http",
      "DownstreamHostAndPorts": [
        {
          "Host": "useridentity.api",
          "Port": 80
        }
      ],
      "UpstreamPathTemplate": "/api/identity/login",
      "UpstreamHttpMethod": [ "Post" ]
    },
    {
      "DownstreamPathTemplate": "/Account/registration",
      "DownstreamScheme": "http",
      "DownstreamHostAndPorts": [
        {
          "Host": "useridentity.api",
          "Port": 80
        }
      ],
      "UpstreamPathTemplate": "/api/identity/registration",
      "UpstreamHttpMethod": [ "Post" ]
    },
    {
      "DownstreamPathTemplate": "/Account/actual-account",
      "DownstreamScheme": "http",
      "DownstreamHostAndPorts": [
        {
          "Host": "useridentity.api",
          "Port": 80
        }
      ],
      "UpstreamPathTemplate": "/api/identity/actual-account",
      "UpstreamHttpMethod": [ "Get" ],
      "AuthenticationOptions": {
        "AuthenticationProviderKey": "Bearer",
        "AllowedScopes": []
      }
    }
  ]
}